dagster_duckdb/__init__.py
dagster_duckdb/io_manager.py
dagster_duckdb/py.typed
dagster_duckdb/resource.py
dagster_duckdb/version.py
dagster_duckdb-0.28.13.dist-info/licenses/LICENSE
dagster_duckdb-0.28.13.dist-info/METADATA
dagster_duckdb-0.28.13.dist-info/WHEEL
dagster_duckdb-0.28.13.dist-info/top_level.txt
dagster_duckdb-0.28.13.dist-info/RECORD
