Metadata-Version: 2.4
Name: dagster-duckdb
Version: 0.28.13
Summary: Package for DuckDB-specific Dagster framework op and resource components.
Home-page: https://github.com/dagster-io/dagster/tree/master/python_modules/libraries/dagster-duckb
Author: Dagster Labs
Author-email: hello@dagsterlabs.com
License: Apache-2.0
Classifier: Programming Language :: Python :: 3.10
Classifier: License :: OSI Approved :: Apache Software License
Classifier: Operating System :: OS Independent
Requires-Python: >=3.10,<3.15
License-File: LICENSE
Requires-Dist: duckdb
Requires-Dist: dagster==1.12.13
Provides-Extra: pandas
Requires-Dist: pandas<3.0.0; extra == "pandas"
Provides-Extra: pyspark
Requires-Dist: pyspark>=4.1; python_version >= "3.14" and extra == "pyspark"
Requires-Dist: pyspark<4,>=3.5; python_version < "3.14" and extra == "pyspark"
Dynamic: author
Dynamic: author-email
Dynamic: classifier
Dynamic: home-page
Dynamic: license
Dynamic: license-file
Dynamic: provides-extra
Dynamic: requires-dist
Dynamic: requires-python
Dynamic: summary
